[
    {
        "featureType": "administrative",
        "elementType": "geometry",
        "stylers": [
            {
                "visibility": "off"
            }
        ]
    },
    {
        "featureType": "poi",
        "stylers": [
            {
                "visibility": "off"
            }
        ]
    },
    {
        "featureType": "road",
        "elementType": "labels.icon",
        "stylers": [
            {
                "visibility": "off"
            }
        ]
    },
    {
        "featureType": "road.arterial",
        "stylers": [
            {
                "color": "#fbecc1"
            }
        ]
    },
    {
        "featureType": "road.arterial",
        "elementType": "geometry.fill",
        "stylers": [
            {
                "color": "#fbecc1"
            }
        ]
    },
    {
        "featureType": "road.arterial",
        "elementType": "geometry.stroke",
        "stylers": [
            {
                "color": "#f3c444"
            }
        ]
    },
    {
        "featureType": "road.arterial",
        "elementType": "labels.text.fill",
        "stylers": [
            {
                "color": "#1a1919"
            }
        ]
    },
    {
        "featureType": "road.highway",
        "stylers": [
            {
                "color": "#fbecc1"
            }
        ]
    },
    {
        "featureType": "road.highway",
        "elementType": "geometry.fill",
        "stylers": [
            {
                "color": "#fbecc1"
            }
        ]
    },
    {
        "featureType": "road.highway",
        "elementType": "geometry.stroke",
        "stylers": [
            {
                "color": "#eab41f"
            }
        ]
    },
    {
        "featureType": "road.highway",
        "elementType": "labels.text",
        "stylers": [
            {
                "color": "#413e3e"
            }
        ]
    },
    {
        "featureType": "road.highway",
        "elementType": "labels.text.fill",
        "stylers": [
            {
                "color": "#050505"
            }
        ]
    },
    {
        "featureType": "road.highway",
        "elementType": "labels.text.stroke",
        "stylers": [
            {
                "color": "#f3f1f1"
            }
        ]
    },
    {
        "featureType": "road.local",
        "elementType": "geometry.fill",
        "stylers": [
            {
                "color": "#fdfcfc"
            }
        ]
    },
    {
        "featureType": "road.local",
        "elementType": "geometry.stroke",
        "stylers": [
            {
                "color": "#e0dcdc"
            }
        ]
    },
    {
        "featureType": "transit",
        "stylers": [
            {
                "visibility": "off"
            }
        ]
    }
]